coreforecast/__init__.py
coreforecast/_lib.cp312-win_amd64.pyd
coreforecast/differences.py
coreforecast/expanding.py
coreforecast/exponentially_weighted.py
coreforecast/grouped_array.py
coreforecast/lag_transforms.py
coreforecast/rolling.py
coreforecast/scalers.py
coreforecast/seasonal.py
coreforecast/utils.py
coreforecast-0.0.14.dist-info/METADATA
coreforecast-0.0.14.dist-info/WHEEL
coreforecast-0.0.14.dist-info/licenses/LICENSE
coreforecast-0.0.14.dist-info/RECORD
