Metadata-Version: 2.1
Name: coreforecast
Version: 0.0.14
Summary: Fast implementations of common forecasting routines
Keywords: forecasting,time-series
Home-page: https://nixtla.github.io/coreforecast
Author-Email: Jose Morales <jmoralz92@gmail.com>
License: Apache-2.0
Classifier: Development Status :: 3 - Alpha
Classifier: Intended Audience :: Science/Research
Classifier: License :: OSI Approved :: Apache Software License
Classifier: Natural Language :: English
Classifier: Programming Language :: Python :: 3.9
Classifier: Programming Language :: Python :: 3.10
Classifier: Programming Language :: Python :: 3.11
Classifier: Programming Language :: Python :: 3.12
Classifier: Programming Language :: Python :: 3.13
Project-URL: Homepage, https://nixtla.github.io/coreforecast
Project-URL: Documentation, https://nixtla.github.io/coreforecast
Project-URL: Repository, https://github.com/Nixtla/coreforecast
Requires-Python: >=3.9
Requires-Dist: numpy>=1.20.0
Requires-Dist: pandas; extra == "dev"
Requires-Dist: pre-commit; extra == "dev"
Requires-Dist: pytest; extra == "dev"
Provides-Extra: dev
